dbt/adapters/sqlserver/__init__.py
dbt/adapters/sqlserver/__version__.py
dbt/adapters/sqlserver/sqlserver_adapter.py
dbt/adapters/sqlserver/sqlserver_column.py
dbt/adapters/sqlserver/sqlserver_configs.py
dbt/adapters/sqlserver/sqlserver_connections.py
dbt/adapters/sqlserver/sqlserver_credentials.py
dbt/adapters/sqlserver/sqlserver_relation.py
dbt/adapters/sqlserver/relation_configs/__init__.py
dbt/adapters/sqlserver/relation_configs/policies.py
dbt/include/sqlserver/__init__.py
dbt/include/sqlserver/dbt_project.yml
dbt/include/sqlserver/profile_template.yml
dbt/include/sqlserver/macros/readme.md
dbt/include/sqlserver/macros/adapter/catalog.sql
dbt/include/sqlserver/macros/adapter/columns.sql
dbt/include/sqlserver/macros/adapter/indexes.sql
dbt/include/sqlserver/macros/adapter/metadata.sql
dbt/include/sqlserver/macros/adapter/relation.sql
dbt/include/sqlserver/macros/adapter/schemas.sql
dbt/include/sqlserver/macros/adapter/validate_sql.sql
dbt/include/sqlserver/macros/materializations/tests.sql
dbt/include/sqlserver/macros/materializations/unit_tests.sql
dbt/include/sqlserver/macros/materializations/models/incremental/incremental.sql
dbt/include/sqlserver/macros/materializations/models/incremental/merge.sql
dbt/include/sqlserver/macros/materializations/models/table/table.sql
dbt/include/sqlserver/macros/materializations/models/view/view.sql
dbt/include/sqlserver/macros/materializations/snapshot/helpers.sql
dbt/include/sqlserver/macros/materializations/snapshot/snapshot.sql
dbt/include/sqlserver/macros/materializations/snapshot/snapshot_merge.sql
dbt/include/sqlserver/macros/relations/seeds/helpers.sql
dbt/include/sqlserver/macros/relations/table/clone.sql
dbt/include/sqlserver/macros/relations/table/create.sql
dbt/include/sqlserver/macros/relations/views/create.sql
dbt/include/sqlserver/macros/utils/split_part.sql
dbt_sqlserver-1.9.0.dist-info/LICENSE
dbt_sqlserver-1.9.0.dist-info/METADATA
dbt_sqlserver-1.9.0.dist-info/WHEEL
dbt_sqlserver-1.9.0.dist-info/top_level.txt
dbt_sqlserver-1.9.0.dist-info/RECORD
